DMLABBasicCal
